dnstap_dashboard/__init__.py
dnstap_dashboard/dashboard.conf
dnstap_dashboard/dashboard.py
dnstap_dashboard-0.2.0.dist-info/LICENSE
dnstap_dashboard-0.2.0.dist-info/METADATA
dnstap_dashboard-0.2.0.dist-info/WHEEL
dnstap_dashboard-0.2.0.dist-info/entry_points.txt
dnstap_dashboard-0.2.0.dist-info/top_level.txt
dnstap_dashboard-0.2.0.dist-info/RECORD
