Metadata-Version: 2.1
Name: dnstap-dashboard
Version: 0.2.0
Summary: dnstap dashboard - real-time metrics for dns server
Home-page: https://github.com/dmachard/dnstap-dashboard
Author: Denis MACHARD
Author-email: d.machard@gmail.com
License: UNKNOWN
Keywords: dnstap dashboard dns metrics
Platform: any
Classifier: License :: OSI Approved :: MIT License
Classifier: Programming Language :: Python :: 3
Classifier: Operating System :: OS Independent
Classifier: Topic :: Software Development :: Libraries
Requires-Dist: pyyaml
Requires-Dist: requests
